GuiPad/GuiPad.py
GuiPad/__init__.py
GuiPad-1.2.2.dist-info/LICENSE
GuiPad-1.2.2.dist-info/METADATA
GuiPad-1.2.2.dist-info/WHEEL
GuiPad-1.2.2.dist-info/top_level.txt
GuiPad-1.2.2.dist-info/RECORD
