Metadata-Version: 2.1
Name: GuiPad
Version: 1.2.2
Summary: Use your gamepad as a mouse with pygame and PyAutoGUI.
Home-page: https://github.com/JackLawrenceCRISPR/GuiPad
Author: Jack Lawrence
Author-email: <JackLawrenceCRISPR@gmail.com>
License: MIT
Keywords: python,pygame,pyautogui,gamepad
Classifier: Development Status :: 5 - Production/Stable
Classifier: Intended Audience :: End Users/Desktop
Classifier: Programming Language :: Python :: 3
Classifier: Operating System :: Unix
Classifier: Operating System :: MacOS :: MacOS X
Classifier: Operating System :: Microsoft :: Windows
Classifier: License :: OSI Approved :: MIT License
Classifier: Natural Language :: English
Requires-Python: >=3.0
License-File: LICENSE
Requires-Dist: pygame >=2.0.0
Requires-Dist: pyautogui >0.9.0
